django_gcm_android_ios-1.0.0.dist-info/DESCRIPTION.rst
django_gcm_android_ios-1.0.0.dist-info/METADATA
django_gcm_android_ios-1.0.0.dist-info/metadata.json
django_gcm_android_ios-1.0.0.dist-info/pbr.json
django_gcm_android_ios-1.0.0.dist-info/RECORD
django_gcm_android_ios-1.0.0.dist-info/top_level.txt
django_gcm_android_ios-1.0.0.dist-info/WHEEL
gcm/__init__.py
gcm/admin.py
gcm/api.py
gcm/models.py
gcm/routers.py
gcm/serializers.py
gcm/settings.py
gcm/tests.py
gcm/utils.py
gcm/migrations/0001_initial.py
gcm/migrations/__init__.py
