Metadata-Version: 2.0
Name: django-gcm-android-ios
Version: 1.0.0
Summary: Send a message using GCM HTTP connection server protocol
Home-page: https://github.com/hugobrilhante/django-gcm-android-ios
Author: Hugo Brilhante
Author-email: hugobrilhante@gmail.com
License: MIT
Platform: UNKNOWN
Classifier: Framework :: Django
Classifier: Intended Audience :: Developers
Classifier: Intended Audience :: System Administrators
Classifier: Operating System :: OS Independent
Classifier: Topic :: Software Development
Classifier: Programming Language :: Python :: 2.7
Classifier: Programming Language :: Python :: 3.4
Requires-Dist: Django (>=1.7)
Requires-Dist: djangorestframework (==3.1.3)
Requires-Dist: mock (==1.0.1)
Requires-Dist: pytz (==2015.4)
Requires-Dist: requests (==2.7.0)
